plover_per_application_state/__init__.py
plover_per_application_state/command.py
plover_per_application_state/extension.py
plover_per_application_state/state/__init__.py
plover_per_application_state/state/manager.py
plover_per_application_state/state/window_state_collection.py
plover_per_application_state/transition/__init__.py
plover_per_application_state/transition/details.py
plover_per_application_state/transition/handler/__init__.py
plover_per_application_state/transition/handler/default.py
plover_per_application_state/transition/handler/dynamic_title.py
plover_per_application_state/transition/handler/handler.py
plover_per_application_state-1.3.1.dist-info/LICENSE
plover_per_application_state-1.3.1.dist-info/METADATA
plover_per_application_state-1.3.1.dist-info/WHEEL
plover_per_application_state-1.3.1.dist-info/entry_points.txt
plover_per_application_state-1.3.1.dist-info/top_level.txt
plover_per_application_state-1.3.1.dist-info/zip-safe
plover_per_application_state-1.3.1.dist-info/RECORD
