Metadata-Version: 2.1
Name: plover-per-application-state
Version: 1.3.1
Summary: Plover plugin to make translation state function per application window and tab
Home-page: https://github.com/Pipatooa/plover-per-application-state
Author: Pipatooa
Author-email: pipatooa@pipatooa.co.uk
Keywords: plover plover_plugin
Requires-Python: >=3.7
License-File: LICENSE
Requires-Dist: plover (>=4.0.0dev12)
Requires-Dist: plover-application-controls (>=1.2.0)
